MANIFEST.in
README.txt
setup.cfg
setup.py
docs/HISTORY.txt
docs/INSTALL.txt
docs/LICENSE.GPL
docs/LICENSE.txt
docs/Makefile
docs/conf.py
docs/index.rst
docs/make.bat
docs/resources/flowsearch.png
redomino/__init__.py
redomino/__init__.pyc
redomino.flowsearch.egg-info/PKG-INFO
redomino.flowsearch.egg-info/SOURCES.txt
redomino.flowsearch.egg-info/dependency_links.txt
redomino.flowsearch.egg-info/entry_points.txt
redomino.flowsearch.egg-info/namespace_packages.txt
redomino.flowsearch.egg-info/not-zip-safe
redomino.flowsearch.egg-info/requires.txt
redomino.flowsearch.egg-info/top_level.txt
redomino/flowsearch/__init__.py
redomino/flowsearch/configure.zcml
redomino/flowsearch/i18n.sh
redomino/flowsearch/tests.py
redomino/flowsearch/browser/__init__.py
redomino/flowsearch/browser/configure.zcml
redomino/flowsearch/browser/flowsearch_view.pt
redomino/flowsearch/browser/flowsearch_view.py
redomino/flowsearch/browser/interfaces.py
redomino/flowsearch/browser/search.pt
redomino/flowsearch/browser/search.py
redomino/flowsearch/browser/search_form.pt
redomino/flowsearch/browser/searchbox.pt
redomino/flowsearch/browser/resources/flowsearch.js
redomino/flowsearch/browser/resources/jquery.deserialize.js
redomino/flowsearch/browser/resources/tabs.css
redomino/flowsearch/locales/redomino.flowsearch.pot
redomino/flowsearch/locales/it/LC_MESSAGES/redomino.flowsearch.po
redomino/flowsearch/profiles/default/browserlayer.xml
redomino/flowsearch/profiles/default/cssregistry.xml
redomino/flowsearch/profiles/default/metadata.xml
redomino/flowsearch/profiles/default/types.xml
redomino/flowsearch/profiles/default/types/Folder.xml
redomino/flowsearch/profiles/default/types/Plone_Site.xml