Metadata-Version: 1.0
Name: redomino.flowsearch
Version: 0.12
Summary: Redomino Flowsearch is a new plugin for Plone CMS that provides an advanced search view
Home-page: https://github.com/redomino/redomino.flowsearch
Author: Maurizio Lupo
Author-email: maurizio.lupo@redomino.com
License: GPL
Keywords: plone search
Platform: UNKNOWN
Classifier: Framework :: Plone
Classifier: Programming Language :: Python
